ncrystal_notebook_utilities/__init__.py
ncrystal_notebook_utilities/download.py
ncrystal_notebook_utilities/endf2ace.py
ncrystal_notebook_utilities/openmc.py
ncrystal_notebook_utilities-0.0.1.dist-info/licenses/LICENSE
ncrystal_notebook_utilities-0.0.1.dist-info/METADATA
ncrystal_notebook_utilities-0.0.1.dist-info/WHEEL
ncrystal_notebook_utilities-0.0.1.dist-info/top_level.txt
ncrystal_notebook_utilities-0.0.1.dist-info/RECORD
