Metadata-Version: 2.4
Name: ncrystal-notebook-utilities
Version: 0.0.1
Summary: Various utilities needed in NCrystal notebook examples.
Author: NCrystal developers
License:                                  Apache License
Project-URL: Homepage, https://github.com/mctools/ncrystal-notebooks
Project-URL: Bug Tracker, https://github.com/mctools/ncrystal/issues
Classifier: Programming Language :: Python :: 3
Classifier: License :: OSI Approved :: Apache Software License
Requires-Python: >=3.9
License-File: LICENSE
Dynamic: license-file
